LICENSE
README.md
setup.py
HiveNetWebUtils/__init__.py
HiveNetWebUtils/auth.py
HiveNetWebUtils/client.py
HiveNetWebUtils/connection_pool.py
HiveNetWebUtils/server.py
HiveNetWebUtils.egg-info/PKG-INFO
HiveNetWebUtils.egg-info/SOURCES.txt
HiveNetWebUtils.egg-info/dependency_links.txt
HiveNetWebUtils.egg-info/not-zip-safe
HiveNetWebUtils.egg-info/requires.txt
HiveNetWebUtils.egg-info/top_level.txt
HiveNetWebUtils/i18n/__init__.py
HiveNetWebUtils/i18n/socket_server_en.json
HiveNetWebUtils/i18n/socket_server_zh.json
HiveNetWebUtils/parser/__init__.py
HiveNetWebUtils/parser/html.py
HiveNetWebUtils/utils/__init__.py
HiveNetWebUtils/utils/cryptography.py
HiveNetWebUtils/utils/socket.py